trilly/__init__.py
trilly/audio_tools.py
twingenio_trilly-1.0.0.dist-info/METADATA
twingenio_trilly-1.0.0.dist-info/WHEEL
twingenio_trilly-1.0.0.dist-info/top_level.txt
twingenio_trilly-1.0.0.dist-info/RECORD
